fs1/__init__.py
fs1/appdirfs.py
fs1/appdirs.py
fs1/base.py
fs1/browsewin.py
fs1/compatibility.py
fs1/errors.py
fs1/filelike.py
fs1/ftpfs.py
fs1/httpfs.py
fs1/iotools.py
fs1/local_functools.py
fs1/memoryfs.py
fs1/mountfs.py
fs1/multifs.py
fs1/opener.py
fs1/path.py
fs1/remote.py
fs1/remotefs.py
fs1/rpcfs.py
fs1/s3fs.py
fs1/sftpfs.py
fs1/tempfs.py
fs1/utils.py
fs1/watch.py
fs1/xattrs.py
fs1/zipfs.py
fs1/commands/__init__.py
fs1/commands/fscat.py
fs1/commands/fscp.py
fs1/commands/fsinfo.py
fs1/commands/fsls.py
fs1/commands/fsmkdir.py
fs1/commands/fsmount.py
fs1/commands/fsmv.py
fs1/commands/fsrm.py
fs1/commands/fsserve.py
fs1/commands/fstree.py
fs1/commands/runner.py
fs1/contrib/__init__.py
fs1/contrib/archivefs.py
fs1/contrib/sqlitefs.py
fs1/contrib/bigfs/__init__.py
fs1/contrib/bigfs/subrangefile.py
fs1/contrib/davfs/__init__.py
fs1/contrib/davfs/util.py
fs1/contrib/davfs/xmlobj.py
fs1/contrib/tahoelafs/__init__.py
fs1/contrib/tahoelafs/connection.py
fs1/contrib/tahoelafs/test_tahoelafs.py
fs1/contrib/tahoelafs/util.py
fs1/expose/__init__.py
fs1/expose/django_storage.py
fs1/expose/ftp.py
fs1/expose/http.py
fs1/expose/importhook.py
fs1/expose/sftp.py
fs1/expose/xmlrpc.py
fs1/expose/dokan/__init__.py
fs1/expose/dokan/libdokan.py
fs1/expose/fuse/__init__.py
fs1/expose/fuse/fuse.py
fs1/expose/fuse/fuse3.py
fs1/expose/fuse/fuse_ctypes.py
fs1/expose/wsgi/__init__.py
fs1/expose/wsgi/dirtemplate.py
fs1/expose/wsgi/serve_home.py
fs1/expose/wsgi/wsgi.py
fs1/osfs/__init__.py
fs1/osfs/watch.py
fs1/osfs/watch_inotify.py
fs1/osfs/watch_win32.py
fs1/osfs/xattrs.py
fs1/tests/__init__.py
fs1/tests/test_archivefs.py
fs1/tests/test_errors.py
fs1/tests/test_expose.py
fs1/tests/test_fs.py
fs1/tests/test_ftpfs.py
fs1/tests/test_importhook.py
fs1/tests/test_iotools.py
fs1/tests/test_mountfs.py
fs1/tests/test_multifs.py
fs1/tests/test_opener.py
fs1/tests/test_path.py
fs1/tests/test_remote.py
fs1-0.6.0.dist-info/DESCRIPTION.rst
fs1-0.6.0.dist-info/METADATA
fs1-0.6.0.dist-info/RECORD
fs1-0.6.0.dist-info/WHEEL
fs1-0.6.0.dist-info/entry_points.txt
fs1-0.6.0.dist-info/metadata.json
fs1-0.6.0.dist-info/top_level.txt
