Metadata-Version: 2.0
Name: fs1
Version: 0.6.0
Summary: Filesystem abstraction layer
Home-page: http://pypi.python.org/pypi/fs/
Author: Will McGugan
Author-email: will@willmcgugan.com
License: BSD
Platform: any
Classifier: Development Status :: 5 - Production/Stable
Classifier: Intended Audience :: Developers
Classifier: License :: OSI Approved :: BSD License
Classifier: Operating System :: OS Independent
Classifier: Programming Language :: Python
Classifier: Programming Language :: Python :: 2.6
Classifier: Programming Language :: Python :: 2.7
Classifier: Programming Language :: Python :: 3
Classifier: Topic :: System :: Filesystems
Requires-Dist: setuptools
Requires-Dist: six
